multirpc/__init__.py
multirpc/exceptions.py
multirpc/multi_rpc_interface.py
multirpc/utils.py
multirpc-1.0.0.dist-info/LICENCE
multirpc-1.0.0.dist-info/METADATA
multirpc-1.0.0.dist-info/WHEEL
multirpc-1.0.0.dist-info/top_level.txt
multirpc-1.0.0.dist-info/RECORD
